setup.py
licecomb/__init__.py
licecomb.egg-info/PKG-INFO
licecomb.egg-info/SOURCES.txt
licecomb.egg-info/dependency_links.txt
licecomb.egg-info/entry_points.txt
licecomb.egg-info/requires.txt
licecomb.egg-info/top_level.txt