Metadata-Version: 1.0
Name: licecomb
Version: 0.1
Summary: Check GitHub repositories for license files
Home-page: https://github.com/doismellburning/licecomb
Author: Kristian Glass
Author-email: licecomb@doismellburning.co.uk
License: mit
Platform: UNKNOWN
